pyperbolic/__init__.py
pyperbolic/metric.py
pyperbolic/point.py
pyperbolic/util.py
tests/__init__.py
tests/test_point.py
tests/test_util.py
pyperbolic-0.0.1.dist-info/LICENSE
pyperbolic-0.0.1.dist-info/METADATA
pyperbolic-0.0.1.dist-info/WHEEL
pyperbolic-0.0.1.dist-info/top_level.txt
pyperbolic-0.0.1.dist-info/RECORD
