Metadata-Version: 2.1
Name: pyperbolic
Version: 0.0.1
Summary: Hyperbolic geometry in Python
Home-page: http://github.com/JWKennington/pyperbolic
Author: James W. Kennington
Author-email: jameswkennington@gmail.com
License: MIT
Platform: UNKNOWN
